[
  {
    "id": "2ab9c5d96228b2249329fb8e93cc52d1",
    "sport_key": "cricket_odi",
    "sport_title": "One Day Internationals",
    "commence_time": "2024-09-16T07:28:34Z",
    "home_team": "Namibia",
    "away_team": "USA",
    "bookmakers": [
      {
        "key": "leovegas",
        "title": "LeoVegas",
        "last_update": "2024-09-16T10:04:52Z",
        "markets": [
          {
            "key": "h2h",
            "last_update": "2024-09-16T10:04:52Z",
            "outcomes": [
              {
                "name": "Namibia",
                "price": 2.35
              },
              {
                "name": "USA",
                "price": 1.47
              }
            ]
          }
        ]
      },
      {
        "key": "mrgreen",
        "title": "Mr Green",
        "last_update": "2024-09-16T10:04:12Z",
        "markets": [
          {
            "key": "h2h",
            "last_update": "2024-09-16T10:04:12Z",
            "outcomes": [
              {
                "name": "Namibia",
                "price": 2.4
              },
              {
                "name": "USA",
                "price": 1.48
              }
            ]
          }
        ]
      },
      {
        "key": "virginbet",
        "title": "Virgin Bet",
        "last_update": "2024-09-16T10:04:53Z",
        "markets": [
          {
            "key": "h2h",
            "last_update": "2024-09-16T10:04:53Z",
            "outcomes": [
              {
                "name": "Namibia",
                "price": 2.43
              },
              {
                "name": "USA",
                "price": 1.5
              }
            ]
          }
        ]
      },
      {
        "key": "unibet_uk",
        "title": "Unibet",
        "last_update": "2024-09-16T10:04:12Z",
        "markets": [
          {
            "key": "h2h",
            "last_update": "2024-09-16T10:04:12Z",
            "outcomes": [
              {
                "name": "Namibia",
                "price": 2.5
              },
              {
                "name": "USA",
                "price": 1.5
              }
            ]
          }
        ]
      },
      {
        "key": "casumo",
        "title": "Casumo",
        "last_update": "2024-09-16T10:04:12Z",
        "markets": [
          {
            "key": "h2h",
            "last_update": "2024-09-16T10:04:12Z",
            "outcomes": [
              {
                "name": "Namibia",
                "price": 2.5
              },
              {
                "name": "USA",
                "price": 1.5
              }
            ]
          }
        ]
      },
      {
        "key": "livescorebet",
        "title": "LiveScore Bet",
        "last_update": "2024-09-16T10:04:12Z",
        "markets": [
          {
            "key": "h2h",
            "last_update": "2024-09-16T10:04:12Z",
            "outcomes": [
              {
                "name": "Namibia",
                "price": 2.45
              },
              {
                "name": "USA",
                "price": 1.5
              }
            ]
          }
        ]
      },
      {
        "key": "grosvenor",
        "title": "Grosvenor",
        "last_update": "2024-09-16T10:04:12Z",
        "markets": [
          {
            "key": "h2h",
            "last_update": "2024-09-16T10:04:12Z",
            "outcomes": [
              {
                "name": "Namibia",
                "price": 2.43
              },
              {
                "name": "USA",
                "price": 1.49
              }
            ]
          }
        ]
      }
    ]
  },
  {
    "id": "e5bd5e911b636f4e316bceee8047cb0d",
    "sport_key": "cricket_odi",
    "sport_title": "One Day Internationals",
    "commence_time": "2024-09-16T14:00:00Z",
    "home_team": "Canada",
    "away_team": "Nepal",
    "bookmakers": [
      {
        "key": "leovegas",
        "title": "LeoVegas",
        "last_update": "2024-09-16T10:04:52Z",
        "markets": [
          {
            "key": "h2h",
            "last_update": "2024-09-16T10:04:52Z",
            "outcomes": [
              {
                "name": "Canada",
                "price": 2.28
              },
              {
                "name": "Nepal",
                "price": 1.5
              }
            ]
          }
        ]
      },
      {
        "key": "mrgreen",
        "title": "Mr Green",
        "last_update": "2024-09-16T10:04:12Z",
        "markets": [
          {
            "key": "h2h",
            "last_update": "2024-09-16T10:04:12Z",
            "outcomes": [
              {
                "name": "Canada",
                "price": 2.3
              },
              {
                "name": "Nepal",
                "price": 1.53
              }
            ]
          }
        ]
      },
      {
        "key": "virginbet",
        "title": "Virgin Bet",
        "last_update": "2024-09-16T10:04:53Z",
        "markets": [
          {
            "key": "h2h",
            "last_update": "2024-09-16T10:04:53Z",
            "outcomes": [
              {
                "name": "Canada",
                "price": 2.35
              },
              {
                "name": "Nepal",
                "price": 1.56
              }
            ]
          }
        ]
      },
      {
        "key": "unibet_uk",
        "title": "Unibet",
        "last_update": "2024-09-16T10:04:12Z",
        "markets": [
          {
            "key": "h2h",
            "last_update": "2024-09-16T10:04:12Z",
            "outcomes": [
              {
                "name": "Canada",
                "price": 2.35
              },
              {
                "name": "Nepal",
                "price": 1.56
              }
            ]
          }
        ]
      },
      {
        "key": "casumo",
        "title": "Casumo",
        "last_update": "2024-09-16T10:04:12Z",
        "markets": [
          {
            "key": "h2h",
            "last_update": "2024-09-16T10:04:12Z",
            "outcomes": [
              {
                "name": "Canada",
                "price": 2.35
              },
              {
                "name": "Nepal",
                "price": 1.56
              }
            ]
          }
        ]
      },
      {
        "key": "livescorebet",
        "title": "LiveScore Bet",
        "last_update": "2024-09-16T10:04:12Z",
        "markets": [
          {
            "key": "h2h",
            "last_update": "2024-09-16T10:04:12Z",
            "outcomes": [
              {
                "name": "Canada",
                "price": 2.35
              },
              {
                "name": "Nepal",
                "price": 1.56
              }
            ]
          }
        ]
      },
      {
        "key": "grosvenor",
        "title": "Grosvenor",
        "last_update": "2024-09-16T10:04:12Z",
        "markets": [
          {
            "key": "h2h",
            "last_update": "2024-09-16T10:04:12Z",
            "outcomes": [
              {
                "name": "Canada",
                "price": 2.35
              },
              {
                "name": "Nepal",
                "price": 1.56
              }
            ]
          }
        ]
      }
    ]
  },
  {
    "id": "eb7fbccd7b4c60918d6eb5d7f2d4770c",
    "sport_key": "cricket_caribbean_premier_league",
    "sport_title": "CPLT20",
    "commence_time": "2024-09-17T23:00:00Z",
    "home_team": "Barbados Royals",
    "away_team": "St Kitts & Nevis Patriots",
    "bookmakers": [
      {
        "key": "betfair_ex_uk",
        "title": "Betfair",
        "last_update": "2024-09-16T10:04:17Z",
        "markets": [
          {
            "key": "h2h",
            "last_update": "2024-09-16T10:04:17Z",
            "outcomes": [
              {
                "name": "Barbados Royals",
                "price": 1.72
              },
              {
                "name": "St Kitts & Nevis Patriots",
                "price": 2.36
              }
            ]
          },
          {
            "key": "h2h_lay",
            "last_update": "2024-09-16T10:04:17Z",
            "outcomes": [
              {
                "name": "Barbados Royals",
                "price": 1.73
              },
              {
                "name": "St Kitts & Nevis Patriots",
                "price": 2.4
              }
            ]
          }
        ]
      },
      {
        "key": "paddypower",
        "title": "Paddy Power",
        "last_update": "2024-09-16T10:04:36Z",
        "markets": [
          {
            "key": "h2h",
            "last_update": "2024-09-16T10:04:36Z",
            "outcomes": [
              {
                "name": "Barbados Royals",
                "price": 1.62
              },
              {
                "name": "St Kitts & Nevis Patriots",
                "price": 2.25
              }
            ]
          }
        ]
      },
      {
        "key": "virginbet",
        "title": "Virgin Bet",
        "last_update": "2024-09-16T10:03:58Z",
        "markets": [
          {
            "key": "h2h",
            "last_update": "2024-09-16T10:03:58Z",
            "outcomes": [
              {
                "name": "Barbados Royals",
                "price": 1.66
              },
              {
                "name": "St Kitts & Nevis Patriots",
                "price": 2.2
              }
            ]
          }
        ]
      },
      {
        "key": "leovegas",
        "title": "LeoVegas",
        "last_update": "2024-09-16T10:04:16Z",
        "markets": [
          {
            "key": "h2h",
            "last_update": "2024-09-16T10:04:16Z",
            "outcomes": [
              {
                "name": "Barbados Royals",
                "price": 1.61
              },
              {
                "name": "St Kitts & Nevis Patriots",
                "price": 2.12
              }
            ]
          }
        ]
      },
      {
        "key": "mrgreen",
        "title": "Mr Green",
        "last_update": "2024-09-16T10:04:36Z",
        "markets": [
          {
            "key": "h2h",
            "last_update": "2024-09-16T10:04:36Z",
            "outcomes": [
              {
                "name": "Barbados Royals",
                "price": 1.62
              },
              {
                "name": "St Kitts & Nevis Patriots",
                "price": 2.15
              }
            ]
          }
        ]
      },
      {
        "key": "casumo",
        "title": "Casumo",
        "last_update": "2024-09-16T10:03:58Z",
        "markets": [
          {
            "key": "h2h",
            "last_update": "2024-09-16T10:03:58Z",
            "outcomes": [
              {
                "name": "Barbados Royals",
                "price": 1.66
              },
              {
                "name": "St Kitts & Nevis Patriots",
                "price": 2.2
              }
            ]
          }
        ]
      },
      {
        "key": "grosvenor",
        "title": "Grosvenor",
        "last_update": "2024-09-16T10:03:58Z",
        "markets": [
          {
            "key": "h2h",
            "last_update": "2024-09-16T10:03:58Z",
            "outcomes": [
              {
                "name": "Barbados Royals",
                "price": 1.66
              },
              {
                "name": "St Kitts & Nevis Patriots",
                "price": 2.2
              }
            ]
          }
        ]
      },
      {
        "key": "unibet_uk",
        "title": "Unibet",
        "last_update": "2024-09-16T10:03:58Z",
        "markets": [
          {
            "key": "h2h",
            "last_update": "2024-09-16T10:03:58Z",
            "outcomes": [
              {
                "name": "Barbados Royals",
                "price": 1.66
              },
              {
                "name": "St Kitts & Nevis Patriots",
                "price": 2.2
              }
            ]
          }
        ]
      },
      {
        "key": "livescorebet",
        "title": "LiveScore Bet",
        "last_update": "2024-09-16T10:04:36Z",
        "markets": [
          {
            "key": "h2h",
            "last_update": "2024-09-16T10:04:36Z",
            "outcomes": [
              {
                "name": "Barbados Royals",
                "price": 1.66
              },
              {
                "name": "St Kitts & Nevis Patriots",
                "price": 2.2
              }
            ]
          }
        ]
      }
    ]
  },
  {
    "id": "03903cf6b174a6cdfcdedbf2b452cdb1",
    "sport_key": "cricket_test_match",
    "sport_title": "Test Matches",
    "commence_time": "2024-09-18T04:30:00Z",
    "home_team": "Sri Lanka",
    "away_team": "New Zealand",
    "bookmakers": [
      {
        "key": "betfair_ex_uk",
        "title": "Betfair",
        "last_update": "2024-09-16T10:04:12Z",
        "markets": [
          {
            "key": "h2h",
            "last_update": "2024-09-16T10:04:12Z",
            "outcomes": [
              {
                "name": "New Zealand",
                "price": 3.95
              },
              {
                "name": "Sri Lanka",
                "price": 2.72
              },
              {
                "name": "Draw",
                "price": 2.56
              }
            ]
          },
          {
            "key": "h2h_lay",
            "last_update": "2024-09-16T10:04:12Z",
            "outcomes": [
              {
                "name": "New Zealand",
                "price": 4.1
              },
              {
                "name": "Sri Lanka",
                "price": 2.78
              },
              {
                "name": "Draw",
                "price": 2.58
              }
            ]
          }
        ]
      },
      {
        "key": "betway",
        "title": "Betway",
        "last_update": "2024-09-16T10:03:56Z",
        "markets": [
          {
            "key": "h2h",
            "last_update": "2024-09-16T10:03:56Z",
            "outcomes": [
              {
                "name": "New Zealand",
                "price": 4.33
              },
              {
                "name": "Sri Lanka",
                "price": 2.4
              },
              {
                "name": "Draw",
                "price": 2.35
              }
            ]
          }
        ]
      },
      {
        "key": "virginbet",
        "title": "Virgin Bet",
        "last_update": "2024-09-16T10:04:31Z",
        "markets": [
          {
            "key": "h2h",
            "last_update": "2024-09-16T10:04:31Z",
            "outcomes": [
              {
                "name": "New Zealand",
                "price": 4.25
              },
              {
                "name": "Sri Lanka",
                "price": 2.5
              },
              {
                "name": "Draw",
                "price": 2.3
              }
            ]
          }
        ]
      },
      {
        "key": "paddypower",
        "title": "Paddy Power",
        "last_update": "2024-09-16T09:54:57Z",
        "markets": [
          {
            "key": "h2h",
            "last_update": "2024-09-16T09:54:57Z",
            "outcomes": [
              {
                "name": "New Zealand",
                "price": 4.33
              },
              {
                "name": "Sri Lanka",
                "price": 2.4
              },
              {
                "name": "Draw",
                "price": 2.3
              }
            ]
          }
        ]
      },
      {
        "key": "livescorebet",
        "title": "LiveScore Bet",
        "last_update": "2024-09-16T10:04:11Z",
        "markets": [
          {
            "key": "h2h",
            "last_update": "2024-09-16T10:04:11Z",
            "outcomes": [
              {
                "name": "New Zealand",
                "price": 4.25
              },
              {
                "name": "Sri Lanka",
                "price": 2.5
              },
              {
                "name": "Draw",
                "price": 2.3
              }
            ]
          }
        ]
      },
      {
        "key": "mrgreen",
        "title": "Mr Green",
        "last_update": "2024-09-16T10:03:49Z",
        "markets": [
          {
            "key": "h2h",
            "last_update": "2024-09-16T10:03:49Z",
            "outcomes": [
              {
                "name": "New Zealand",
                "price": 4.2
              },
              {
                "name": "Sri Lanka",
                "price": 2.45
              },
              {
                "name": "Draw",
                "price": 2.25
              }
            ]
          }
        ]
      },
      {
        "key": "matchbook",
        "title": "Matchbook",
        "last_update": "2024-09-16T10:02:43Z",
        "markets": [
          {
            "key": "h2h",
            "last_update": "2024-09-16T10:02:43Z",
            "outcomes": [
              {
                "name": "New Zealand",
                "price": 3.9
              },
              {
                "name": "Sri Lanka",
                "price": 2.62
              },
              {
                "name": "Draw",
                "price": 2.46
              }
            ]
          },
          {
            "key": "h2h_lay",
            "last_update": "2024-09-16T10:02:43Z",
            "outcomes": [
              {
                "name": "New Zealand",
                "price": 4.4
              },
              {
                "name": "Sri Lanka",
                "price": 2.84
              },
              {
                "name": "Draw",
                "price": 2.66
              }
            ]
          }
        ]
      },
      {
        "key": "boylesports",
        "title": "BoyleSports",
        "last_update": "2024-09-16T10:04:52Z",
        "markets": [
          {
            "key": "h2h",
            "last_update": "2024-09-16T10:04:52Z",
            "outcomes": [
              {
                "name": "New Zealand",
                "price": 4
              },
              {
                "name": "Sri Lanka",
                "price": 2.6
              },
              {
                "name": "Draw",
                "price": 2.25
              }
            ]
          }
        ]
      }
    ]
  },
  {
    "id": "0c121892db40635cb8d04c2e28de4b3a",
    "sport_key": "cricket_odi",
    "sport_title": "One Day Internationals",
    "commence_time": "2024-09-18T12:00:00Z",
    "home_team": "Afghanistan",
    "away_team": "South Africa",
    "bookmakers": [
      {
        "key": "leovegas",
        "title": "LeoVegas",
        "last_update": "2024-09-16T10:04:52Z",
        "markets": [
          {
            "key": "h2h",
            "last_update": "2024-09-16T10:04:52Z",
            "outcomes": [
              {
                "name": "Afghanistan",
                "price": 2.43
              },
              {
                "name": "South Africa",
                "price": 1.47
              }
            ]
          }
        ]
      },
      {
        "key": "mrgreen",
        "title": "Mr Green",
        "last_update": "2024-09-16T10:04:12Z",
        "markets": [
          {
            "key": "h2h",
            "last_update": "2024-09-16T10:04:12Z",
            "outcomes": [
              {
                "name": "Afghanistan",
                "price": 2.45
              },
              {
                "name": "South Africa",
                "price": 1.49
              }
            ]
          }
        ]
      },
      {
        "key": "virginbet",
        "title": "Virgin Bet",
        "last_update": "2024-09-16T10:04:53Z",
        "markets": [
          {
            "key": "h2h",
            "last_update": "2024-09-16T10:04:53Z",
            "outcomes": [
              {
                "name": "Afghanistan",
                "price": 2.5
              },
              {
                "name": "South Africa",
                "price": 1.52
              }
            ]
          }
        ]
      },
      {
        "key": "casumo",
        "title": "Casumo",
        "last_update": "2024-09-16T10:04:12Z",
        "markets": [
          {
            "key": "h2h",
            "last_update": "2024-09-16T10:04:12Z",
            "outcomes": [
              {
                "name": "Afghanistan",
                "price": 2.5
              },
              {
                "name": "South Africa",
                "price": 1.51
              }
            ]
          }
        ]
      },
      {
        "key": "livescorebet",
        "title": "LiveScore Bet",
        "last_update": "2024-09-16T10:04:12Z",
        "markets": [
          {
            "key": "h2h",
            "last_update": "2024-09-16T10:04:12Z",
            "outcomes": [
              {
                "name": "Afghanistan",
                "price": 2.5
              },
              {
                "name": "South Africa",
                "price": 1.52
              }
            ]
          }
        ]
      },
      {
        "key": "grosvenor",
        "title": "Grosvenor",
        "last_update": "2024-09-16T10:04:12Z",
        "markets": [
          {
            "key": "h2h",
            "last_update": "2024-09-16T10:04:12Z",
            "outcomes": [
              {
                "name": "Afghanistan",
                "price": 2.5
              },
              {
                "name": "South Africa",
                "price": 1.51
              }
            ]
          }
        ]
      },
      {
        "key": "unibet_uk",
        "title": "Unibet",
        "last_update": "2024-09-16T10:04:12Z",
        "markets": [
          {
            "key": "h2h",
            "last_update": "2024-09-16T10:04:12Z",
            "outcomes": [
              {
                "name": "Afghanistan",
                "price": 2.5
              },
              {
                "name": "South Africa",
                "price": 1.51
              }
            ]
          }
        ]
      },
      {
        "key": "betfair_ex_uk",
        "title": "Betfair",
        "last_update": "2024-09-16T10:04:53Z",
        "markets": [
          {
            "key": "h2h",
            "last_update": "2024-09-16T10:04:53Z",
            "outcomes": [
              {
                "name": "Afghanistan",
                "price": 2.6
              },
              {
                "name": "South Africa",
                "price": 1.61
              }
            ]
          },
          {
            "key": "h2h_lay",
            "last_update": "2024-09-16T10:04:53Z",
            "outcomes": [
              {
                "name": "Afghanistan",
                "price": 2.64
              },
              {
                "name": "South Africa",
                "price": 1.63
              }
            ]
          }
        ]
      },
      {
        "key": "williamhill",
        "title": "William Hill",
        "last_update": "2024-09-16T10:04:12Z",
        "markets": [
          {
            "key": "h2h",
            "last_update": "2024-09-16T10:04:12Z",
            "outcomes": [
              {
                "name": "Afghanistan",
                "price": 2.5
              },
              {
                "name": "South Africa",
                "price": 1.53
              }
            ]
          }
        ]
      }
    ]
  },
  {
    "id": "ea802365d5e51867bed7ef2c2f56abe2",
    "sport_key": "cricket_caribbean_premier_league",
    "sport_title": "CPLT20",
    "commence_time": "2024-09-18T23:00:00Z",
    "home_team": "Trinbago Knight Riders",
    "away_team": "Guyana Amazon Warriors",
    "bookmakers": [
      {
        "key": "betfair_ex_uk",
        "title": "Betfair",
        "last_update": "2024-09-16T10:04:17Z",
        "markets": [
          {
            "key": "h2h",
            "last_update": "2024-09-16T10:04:17Z",
            "outcomes": [
              {
                "name": "Guyana Amazon Warriors",
                "price": 1.2
              },
              {
                "name": "Trinbago Knight Riders",
                "price": 1.52
              }
            ]
          },
          {
            "key": "h2h_lay",
            "last_update": "2024-09-16T10:04:17Z",
            "outcomes": [
              {
                "name": "Guyana Amazon Warriors",
                "price": 2.98
              },
              {
                "name": "Trinbago Knight Riders",
                "price": 6
              }
            ]
          }
        ]
      },
      {
        "key": "paddypower",
        "title": "Paddy Power",
        "last_update": "2024-09-16T10:04:36Z",
        "markets": [
          {
            "key": "h2h",
            "last_update": "2024-09-16T10:04:36Z",
            "outcomes": [
              {
                "name": "Guyana Amazon Warriors",
                "price": 2.25
              },
              {
                "name": "Trinbago Knight Riders",
                "price": 1.62
              }
            ]
          }
        ]
      },
      {
        "key": "leovegas",
        "title": "LeoVegas",
        "last_update": "2024-09-16T10:04:16Z",
        "markets": [
          {
            "key": "h2h",
            "last_update": "2024-09-16T10:04:16Z",
            "outcomes": [
              {
                "name": "Guyana Amazon Warriors",
                "price": 2.23
              },
              {
                "name": "Trinbago Knight Riders",
                "price": 1.56
              }
            ]
          }
        ]
      },
      {
        "key": "mrgreen",
        "title": "Mr Green",
        "last_update": "2024-09-16T10:04:36Z",
        "markets": [
          {
            "key": "h2h",
            "last_update": "2024-09-16T10:04:36Z",
            "outcomes": [
              {
                "name": "Guyana Amazon Warriors",
                "price": 2.25
              },
              {
                "name": "Trinbago Knight Riders",
                "price": 1.57
              }
            ]
          }
        ]
      },
      {
        "key": "casumo",
        "title": "Casumo",
        "last_update": "2024-09-16T10:03:58Z",
        "markets": [
          {
            "key": "h2h",
            "last_update": "2024-09-16T10:03:58Z",
            "outcomes": [
              {
                "name": "Guyana Amazon Warriors",
                "price": 2.3
              },
              {
                "name": "Trinbago Knight Riders",
                "price": 1.61
              }
            ]
          }
        ]
      },
      {
        "key": "unibet_uk",
        "title": "Unibet",
        "last_update": "2024-09-16T10:03:58Z",
        "markets": [
          {
            "key": "h2h",
            "last_update": "2024-09-16T10:03:58Z",
            "outcomes": [
              {
                "name": "Guyana Amazon Warriors",
                "price": 2.3
              },
              {
                "name": "Trinbago Knight Riders",
                "price": 1.61
              }
            ]
          }
        ]
      },
      {
        "key": "virginbet",
        "title": "Virgin Bet",
        "last_update": "2024-09-16T10:03:58Z",
        "markets": [
          {
            "key": "h2h",
            "last_update": "2024-09-16T10:03:58Z",
            "outcomes": [
              {
                "name": "Guyana Amazon Warriors",
                "price": 2.3
              },
              {
                "name": "Trinbago Knight Riders",
                "price": 1.61
              }
            ]
          }
        ]
      },
      {
        "key": "livescorebet",
        "title": "LiveScore Bet",
        "last_update": "2024-09-16T10:04:36Z",
        "markets": [
          {
            "key": "h2h",
            "last_update": "2024-09-16T10:04:36Z",
            "outcomes": [
              {
                "name": "Guyana Amazon Warriors",
                "price": 2.3
              },
              {
                "name": "Trinbago Knight Riders",
                "price": 1.61
              }
            ]
          }
        ]
      },
      {
        "key": "grosvenor",
        "title": "Grosvenor",
        "last_update": "2024-09-16T10:03:58Z",
        "markets": [
          {
            "key": "h2h",
            "last_update": "2024-09-16T10:03:58Z",
            "outcomes": [
              {
                "name": "Guyana Amazon Warriors",
                "price": 2.3
              },
              {
                "name": "Trinbago Knight Riders",
                "price": 1.61
              }
            ]
          }
        ]
      }
    ]
  },
  {
    "id": "ea1876adfa8f2f11a607f1b89868fdf0",
    "sport_key": "cricket_test_match",
    "sport_title": "Test Matches",
    "commence_time": "2024-09-19T04:00:00Z",
    "home_team": "India",
    "away_team": "Bangladesh",
    "bookmakers": [
      {
        "key": "mrgreen",
        "title": "Mr Green",
        "last_update": "2024-09-16T10:03:49Z",
        "markets": [
          {
            "key": "h2h",
            "last_update": "2024-09-16T10:03:49Z",
            "outcomes": [
              {
                "name": "Bangladesh",
                "price": 12.5
              },
              {
                "name": "India",
                "price": 1.12
              },
              {
                "name": "Draw",
                "price": 8.5
              }
            ]
          }
        ]
      },
      {
        "key": "betfair_ex_uk",
        "title": "Betfair",
        "last_update": "2024-09-16T10:04:12Z",
        "markets": [
          {
            "key": "h2h",
            "last_update": "2024-09-16T10:04:12Z",
            "outcomes": [
              {
                "name": "Bangladesh",
                "price": 17.5
              },
              {
                "name": "India",
                "price": 1.18
              },
              {
                "name": "Draw",
                "price": 9.4
              }
            ]
          },
          {
            "key": "h2h_lay",
            "last_update": "2024-09-16T10:04:12Z",
            "outcomes": [
              {
                "name": "Bangladesh",
                "price": 18.5
              },
              {
                "name": "India",
                "price": 1.19
              },
              {
                "name": "Draw",
                "price": 9.8
              }
            ]
          }
        ]
      },
      {
        "key": "virginbet",
        "title": "Virgin Bet",
        "last_update": "2024-09-16T10:04:31Z",
        "markets": [
          {
            "key": "h2h",
            "last_update": "2024-09-16T10:04:31Z",
            "outcomes": [
              {
                "name": "Bangladesh",
                "price": 13
              },
              {
                "name": "India",
                "price": 1.14
              },
              {
                "name": "Draw",
                "price": 9
              }
            ]
          }
        ]
      },
      {
        "key": "livescorebet",
        "title": "LiveScore Bet",
        "last_update": "2024-09-16T10:04:11Z",
        "markets": [
          {
            "key": "h2h",
            "last_update": "2024-09-16T10:04:11Z",
            "outcomes": [
              {
                "name": "Bangladesh",
                "price": 13
              },
              {
                "name": "India",
                "price": 1.14
              },
              {
                "name": "Draw",
                "price": 9
              }
            ]
          }
        ]
      },
      {
        "key": "paddypower",
        "title": "Paddy Power",
        "last_update": "2024-09-16T10:03:49Z",
        "markets": [
          {
            "key": "h2h",
            "last_update": "2024-09-16T10:03:49Z",
            "outcomes": [
              {
                "name": "Bangladesh",
                "price": 13
              },
              {
                "name": "India",
                "price": 1.14
              },
              {
                "name": "Draw",
                "price": 8
              }
            ]
          }
        ]
      },
      {
        "key": "betway",
        "title": "Betway",
        "last_update": "2024-09-16T10:03:56Z",
        "markets": [
          {
            "key": "h2h",
            "last_update": "2024-09-16T10:03:56Z",
            "outcomes": [
              {
                "name": "Bangladesh",
                "price": 13
              },
              {
                "name": "India",
                "price": 1.17
              },
              {
                "name": "Draw",
                "price": 8
              }
            ]
          }
        ]
      },
      {
        "key": "boylesports",
        "title": "BoyleSports",
        "last_update": "2024-09-16T10:04:52Z",
        "markets": [
          {
            "key": "h2h",
            "last_update": "2024-09-16T10:04:52Z",
            "outcomes": [
              {
                "name": "Bangladesh",
                "price": 12
              },
              {
                "name": "India",
                "price": 1.14
              },
              {
                "name": "Draw",
                "price": 7.5
              }
            ]
          }
        ]
      }
    ]
  }
]